image_str/__init__.py
image_str/parse_images.py
image_str/parse_img.py
image_str/utils.py
image_str-0.0.0.dist-info/METADATA
image_str-0.0.0.dist-info/WHEEL
image_str-0.0.0.dist-info/top_level.txt
image_str-0.0.0.dist-info/RECORD
