Metadata-Version: 2.1
Name: image-str
Version: 0.0.0
Summary: OCR Image Processing for Label Detection and Localization
Home-page: https://github.com/rachlu/isaac
Author: Rachel Lu
Author-email: rachel.lu@nasa.gov
License: UNKNOWN
Platform: UNKNOWN
Classifier: Development Status :: 1 - Planning
Classifier: License :: OSI Approved :: Apache Software License
Classifier: Programming Language :: Python :: 3
Classifier: Operating System :: OS Independent
